<?xml version="1.0" encoding="UTF-8"?>
<seiscomp xmlns="http://geofon.gfz-potsdam.de/ns/seiscomp3-schema/0.13" version="0.13"><Inventory><datalogger publicID="Datalogger/20240716233100.903846.6" name="AT.AKUT.BHZ.2004.322.00.00.00"><gain>1</gain><maxClockDrift>5e-05</maxClockDrift><decimation sampleRateNumerator="50" sampleRateDenominator="1"/></datalogger><network publicID="NET/AT/20240716233100.903182.39" code="AT"><start>1967-01-01T00:00:00.0000Z</start><description>National Tsunami Warning Center Alaska Seismic Network (AT)</description><restricted>false</restricted><shared>true</shared><comment><text>{"type":"DOI","value":"10.7914/SN/AT"}</text><id>FDSNXML:Identifier/0</id></comment><station publicID="STA/AT/AKUT/20240716233100.903422.41" code="AKUT"><start>2004-11-17T00:00:00.0000Z</start><description>Akutan, Alaska</description><latitude>54.13517</latitude><longitude>-165.771851</longitude><elevation>19.2</elevation><restricted>false</restricted><shared>true</shared><comment><text>{"value":"New station first installed 6/2004 (S13)"}</text><id>FDSNXML:Comment/1</id><start>2004-11-17T00:00:00.0000Z</start></comment><sensorLocation publicID="LOC/AT/AKUT//20240716233100.903571.43" code=""><start>2004-11-17T00:00:00.0000Z</start><latitude>54.13517</latitude><longitude>-165.771851</longitude><elevation>19.2</elevation><stream publicID="Stream/20240716233100.903678.5" code="BHZ" datalogger="Datalogger/20240716233100.903846.6"><start>2004-11-17T00:00:00.0000Z</start><dataloggerSerialNumber>xxxx</dataloggerSerialNumber><dataloggerChannel>0</dataloggerChannel><sensorSerialNumber>yyyy</sensorSerialNumber><sensorChannel>0</sensorChannel><sampleRateNumerator>50</sampleRateNumerator><sampleRateDenominator>1</sampleRateDenominator><depth>0</depth><azimuth>0</azimuth><dip>-90</dip><gain>629140000</gain><gainFrequency>1</gainFrequency><gainUnit>M/S</gainUnit><restricted>false</restricted><comment><text>{"value":"STS-2/G3=10431"}</text><id>FDSNXML:Comment/1</id></comment><comment><text>{"description":"STS-2/Trident"}</text><id>FDSNXML:Sensor</id></comment></stream></sensorLocation></station></network></Inventory></seiscomp>
