<?xml version="1.0" encoding="UTF-8"?>
<seiscomp xmlns="http://geofon.gfz-potsdam.de/ns/seiscomp3-schema/0.13" version="0.13"><Inventory><datalogger publicID="Datalogger/20240716233121.631997.6" name="AU.QIS.00BHN.2022.257.00.00.00"><digitizerModel>Centaur</digitizerModel><digitizerManufacturer>Nanometrics</digitizerManufacturer><gain>1</gain><decimation sampleRateNumerator="40" sampleRateDenominator="1"/></datalogger><network publicID="NET/AU/20240716233121.63136.36" code="AU"><start>1994-01-01T00:00:00.0000Z</start><description>Australian National Seismograph Network (ANSN)</description><restricted>false</restricted><shared>true</shared><comment><text>{"type":"DOI","value":"10.26186/144675"}</text><id>FDSNXML:Identifier/0</id></comment><station publicID="STA/AU/QIS/20240716233121.6316.38" code="QIS"><start>2005-02-06T00:00:00.0000Z</start><description>Mount Isa, Qld</description><latitude>-20.557699</latitude><longitude>139.605194</longitude><elevation>450</elevation><restricted>false</restricted><shared>true</shared><sensorLocation publicID="LOC/AU/QIS/00/20240716233121.631737.39" code="00"><start>2022-09-14T00:00:00.0000Z</start><latitude>-20.557699</latitude><longitude>139.605194</longitude><elevation>450</elevation><stream publicID="Stream/20240716233121.631845.5" code="BHN" datalogger="Datalogger/20240716233121.631997.6"><start>2022-09-14T00:00:00.0000Z</start><dataloggerSerialNumber>1714</dataloggerSerialNumber><dataloggerChannel>1</dataloggerChannel><sensorSerialNumber>0000</sensorSerialNumber><sensorChannel>1</sensorChannel><sampleRateNumerator>40</sampleRateNumerator><sampleRateDenominator>1</sampleRateDenominator><depth>57</depth><azimuth>0</azimuth><dip>0</dip><gain>955344000</gain><gainFrequency>0.1</gainFrequency><gainUnit>M/S</gainUnit><restricted>false</restricted><comment><text>{"description":"Geotech KS54000/Quanterra 330HR Linear Phase Below","serialNumber":"0000","resourceId":"Sensor/20220916045717.139609.79"}</text><id>FDSNXML:Sensor</id></comment><comment><text>{"type":"Nanometrics Centaur","manufacturer":"Nanometrics","model":"Centaur","serialNumber":"1714","resourceId":"NRL/Nanometrics/CENTAUR.1.40.OFF.LP"}</text><id>FDSNXML:DataLogger</id></comment></stream></sensorLocation></station></network></Inventory></seiscomp>
