<?xml version="1.0" encoding="UTF-8"?>
<seiscomp xmlns="http://geofon.gfz-potsdam.de/ns/seiscomp3-schema/0.13" version="0.13"><Inventory><datalogger publicID="Datalogger/20240716233658.26718.6" name="N4.Y60A.00HHZ.2021.195.21.49.00"><digitizerModel>Q330</digitizerModel><digitizerManufacturer>QUANTERRA</digitizerManufacturer><gain>1</gain><decimation sampleRateNumerator="100" sampleRateDenominator="1"/></datalogger><network publicID="NET/N4/20240716233658.266526.40" code="N4"><start>2013-01-01T00:00:00.0000Z</start><description>Central and Eastern US Network (CEUSN)</description><restricted>false</restricted><shared>true</shared><comment><text>{"type":"DOI","value":"10.7914/SN/N4"}</text><id>FDSNXML:Identifier/0</id></comment><station publicID="STA/N4/Y60A/20240716233658.266768.42" code="Y60A"><start>2015-01-30T00:00:00.0000Z</start><description>Bolivia, NC, USA</description><latitude>34.0046</latitude><longitude>-78.2163</longitude><elevation>7</elevation><place>NC / Bolivia</place><country>USA</country><restricted>false</restricted><shared>true</shared><sensorLocation publicID="LOC/N4/Y60A/00/20240716233658.266899.43" code="00"><start>2021-07-14T21:49:00.0000Z</start><latitude>34.0046</latitude><longitude>-78.2163</longitude><elevation>7</elevation><stream publicID="Stream/20240716233658.267005.5" code="HHZ" datalogger="Datalogger/20240716233658.26718.6"><start>2021-07-14T21:49:00.0000Z</start><dataloggerSerialNumber>4527</dataloggerSerialNumber><dataloggerChannel>0</dataloggerChannel><sensorSerialNumber>245</sensorSerialNumber><sensorChannel>0</sensorChannel><sampleRateNumerator>100</sampleRateNumerator><sampleRateDenominator>1</sampleRateDenominator><depth>0</depth><azimuth>0</azimuth><dip>-90</dip><gain>497864000</gain><gainFrequency>0.02</gainFrequency><gainUnit>m/s</gainUnit><flags>CG</flags><restricted>false</restricted><comment><text>{"value":"Config Change"}</text><id>FDSNXML:Comment/1</id><start>2021-07-14T21:49:00.0000Z</start></comment><comment><text>{"value":"[LOGGER::Q330::4527]"}</text><id>FDSNXML:Comment/2</id><start>2021-07-14T21:49:00.0000Z</start></comment><comment><text>{"type":"NANOMETRICS","description":"Velocity Sensor","manufacturer":"NANOMETRICS","model":"TRILLIUM 240","serialNumber":"245"}</text><id>FDSNXML:Sensor</id></comment><comment><text>{"type":"QUANTERRA","manufacturer":"QUANTERRA","model":"Q330","serialNumber":"4527"}</text><id>FDSNXML:DataLogger</id></comment></stream></sensorLocation></station></network></Inventory></seiscomp>
