<?xml version="1.0" encoding="UTF-8"?>
<seiscomp xmlns="http://geofon.gfz-potsdam.de/ns/seiscomp3-schema/0.13" version="0.13"><Inventory><datalogger publicID="Datalogger/20240716233700.551842.6" name="NA.SEUS.BHZ.2006.302.00.00.00"><gain>1</gain><maxClockDrift>0.01</maxClockDrift><decimation sampleRateNumerator="40" sampleRateDenominator="1"/></datalogger><network publicID="NET/NA/20240716233700.551212.39" code="NA"><start>2006-01-01T00:00:00.0000Z</start><description>Caribbean Netherlands Seismic Network ()</description><restricted>false</restricted><shared>true</shared><comment><text>{"type":"DOI","value":"10.21944/dffa7a3f-7e3a-3b33-a436-516a01b6af3f"}</text><id>FDSNXML:Identifier/0</id></comment><station publicID="STA/NA/SEUS/20240716233700.551445.41" code="SEUS"><start>2006-10-29T00:00:00.0000Z</start><description>St Eustatius, Netherlands Antilles Seismic Network</description><latitude>17.4928</latitude><longitude>-62.9814</longitude><elevation>46</elevation><restricted>false</restricted><shared>true</shared><sensorLocation publicID="LOC/NA/SEUS//20240716233700.551573.42" code=""><start>2006-10-29T00:00:00.0000Z</start><latitude>17.4928</latitude><longitude>-62.9814</longitude><elevation>46</elevation><stream publicID="Stream/20240716233700.551678.5" code="BHZ" datalogger="Datalogger/20240716233700.551842.6"><start>2006-10-29T00:00:00.0000Z</start><dataloggerSerialNumber>xxxx</dataloggerSerialNumber><dataloggerChannel>0</dataloggerChannel><sensorSerialNumber>yyyy</sensorSerialNumber><sensorChannel>0</sensorChannel><sampleRateNumerator>40</sampleRateNumerator><sampleRateDenominator>1</sampleRateDenominator><depth>0</depth><azimuth>0</azimuth><dip>-90</dip><gain>627192000</gain><gainFrequency>0.2</gainFrequency><gainUnit>M/S</gainUnit><flags>G</flags><restricted>false</restricted><comment><text>{"value":"50001 0003"}</text><id>FDSNXML:Comment/1</id></comment><comment><text>{"description":"Streckeisen STS-2 G3/Quanterra 330 Linear Phase Co"}</text><id>FDSNXML:Sensor</id></comment></stream></sensorLocation></station></network></Inventory></seiscomp>
