<?xml version="1.0" encoding="UTF-8"?>
<seiscomp xmlns="http://geofon.gfz-potsdam.de/ns/seiscomp3-schema/0.13" version="0.13"><Inventory><datalogger publicID="Datalogger/20240716233746.77045.6" name="PA.BRU2.HHZ.2000.001.00.00.00"><gain>1</gain><maxClockDrift>0</maxClockDrift><decimation sampleRateNumerator="100" sampleRateDenominator="1"/></datalogger><network publicID="NET/PA/20240716233746.769828.40" code="PA"><start>2000-01-01T00:00:00.0000Z</start><description>ChiriNet ()</description><restricted>false</restricted><shared>true</shared><comment><text>{"type":"DOI","value":"10.7914/SN/PA"}</text><id>FDSNXML:Identifier/0</id></comment><station publicID="STA/PA/BRU2/20240716233746.770063.42" code="BRU2"><start>2000-01-01T00:00:00.0000Z</start><description>bru2, Barilles, OSOP, Panama</description><latitude>8.794</latitude><longitude>-82.687798</longitude><elevation>1320</elevation><restricted>false</restricted><shared>true</shared><sensorLocation publicID="LOC/PA/BRU2//20240716233746.770189.43" code=""><start>2000-01-01T00:00:00.0000Z</start><latitude>8.794</latitude><longitude>-82.687798</longitude><elevation>1320</elevation><stream publicID="Stream/20240716233746.77029.5" code="HHZ" datalogger="Datalogger/20240716233746.77045.6"><start>2000-01-01T00:00:00.0000Z</start><dataloggerSerialNumber>xxxx</dataloggerSerialNumber><dataloggerChannel>0</dataloggerChannel><sensorSerialNumber>yyyy</sensorSerialNumber><sensorChannel>0</sensorChannel><sampleRateNumerator>100</sampleRateNumerator><sampleRateDenominator>1</sampleRateDenominator><depth>0</depth><azimuth>0</azimuth><dip>-90</dip><gain>299572000</gain><gainFrequency>0.05</gainFrequency><gainUnit>M/S</gainUnit><flags>CG</flags><restricted>false</restricted><comment><text>{"value":"X"}</text><id>FDSNXML:Comment/1</id></comment><comment><text>{"description":"Trillium Compact, 120 s, 749 V/m/s-EDR-209, Very L"}</text><id>FDSNXML:Sensor</id></comment></stream></sensorLocation></station></network></Inventory></seiscomp>
