<?xml version="1.0" encoding="UTF-8"?>
<seiscomp xmlns="http://geofon.gfz-potsdam.de/ns/seiscomp3-schema/0.13" version="0.13"><Inventory><datalogger publicID="Datalogger/20240716233833.608677.6" name="SV.SNET.BHZ.2004.001.00.00.00"><gain>1</gain><maxClockDrift>5e-05</maxClockDrift><decimation sampleRateNumerator="20" sampleRateDenominator="1"/></datalogger><network publicID="NET/SV/20240716233833.608088.36" code="SV"><start>2004-01-01T00:00:00.0000Z</start><description>Servicio Nacional de Estudios Territoriales (SNET), El Salvador (SNET-BB)</description><restricted>false</restricted><shared>true</shared><station publicID="STA/SV/SNET/20240716233833.608281.37" code="SNET"><start>2004-01-01T00:00:00.0000Z</start><description>Montecristo, El Salvador</description><latitude>13.6868</latitude><longitude>-89.231499</longitude><elevation>775</elevation><restricted>false</restricted><shared>true</shared><sensorLocation publicID="LOC/SV/SNET//20240716233833.608407.38" code=""><start>2004-01-01T00:00:00.0000Z</start><latitude>13.6868</latitude><longitude>-89.231499</longitude><elevation>775</elevation><stream publicID="Stream/20240716233833.608512.5" code="BHZ" datalogger="Datalogger/20240716233833.608677.6"><start>2004-01-01T00:00:00.0000Z</start><dataloggerSerialNumber>xxxx</dataloggerSerialNumber><dataloggerChannel>0</dataloggerChannel><sensorSerialNumber>yyyy</sensorSerialNumber><sensorChannel>0</sensorChannel><sampleRateNumerator>20</sampleRateNumerator><sampleRateDenominator>1</sampleRateDenominator><depth>0</depth><azimuth>0</azimuth><dip>-90</dip><gain>629145000</gain><gainFrequency>0.05</gainFrequency><gainUnit>M/S</gainUnit><restricted>false</restricted><comment><text>{"description":"STS-2, 120 s, 1500 V/m/s, generation 3 electronics"}</text><id>FDSNXML:Sensor</id></comment></stream></sensorLocation></station></network></Inventory></seiscomp>
